CHANGELOG.md
README.md
mitol/__init__.py
mitol/mail/__init__.py
mitol/mail/api.py
mitol/mail/apps.py
mitol/mail/defaults.py
mitol/mail/forms.py
mitol/mail/messages.py
mitol/mail/py.typed
mitol/mail/urls.py
mitol/mail/views.py
mitol/mail/settings/__init__.py
mitol/mail/settings/email.py
mitol/mail/templates/mail/email_base.html
mitol/mail/templates/mail/email_debugger.html
mitol/mail/templates/mail/partials/_logo.html
mitol_django_mail-2025.6.24.dist-info/METADATA
mitol_django_mail-2025.6.24.dist-info/WHEEL
mitol_django_mail-2025.6.24.dist-info/RECORD
