Metadata-Version: 2.4
Name: mitol-django-mail
Version: 2025.6.24
Summary: MIT Open Learning django app extensions for mail
License-Expression: BSD-3-Clause
Requires-Python: >=3.10
Requires-Dist: beautifulsoup4>=4.6.0
Requires-Dist: django-anymail>=6.0
Requires-Dist: django-stubs>=1.13.1
Requires-Dist: django>=3.0
Requires-Dist: html5lib>=1.1
Requires-Dist: mitol-django-common
Requires-Dist: premailer>=3.7.0
Requires-Dist: toolz>=0.10.0
